fire_prox/__init__.py
fire_prox/aggregation.py
fire_prox/async_fire_collection.py
fire_prox/async_fire_object.py
fire_prox/async_fire_query.py
fire_prox/async_fireprox.py
fire_prox/base_fire_collection.py
fire_prox/base_fire_object.py
fire_prox/base_fireprox.py
fire_prox/fire_collection.py
fire_prox/fire_object.py
fire_prox/fire_query.py
fire_prox/fire_vector.py
fire_prox/fireprox.py
fire_prox/py.typed
fire_prox/state.py
fire_prox/testing/__init__.py
fire_prox-0.3.0.dist-info/METADATA
fire_prox-0.3.0.dist-info/WHEEL
fire_prox-0.3.0.dist-info/licenses/LICENSE
fire_prox-0.3.0.dist-info/RECORD
