Metadata-Version: 2.4
Name: fire-prox
Version: 0.3.0
Summary: Fast prototyping for FireStore
Project-URL: Homepage, https://github.com/habemus-papadum/fire-prox
Project-URL: Repository, https://github.com/habemus-papadum/fire-prox
Project-URL: Documentation, https://github.com/habemus-papadum/fire-prox
Author-email: Nehal Patel <nehal@alum.mit.edu>
License: MIT License
License-File: LICENSE
Keywords: firebase,firestore
Requires-Python: >=3.12
Requires-Dist: google-cloud-firestore>=2.21.0
